ants/internal.py
ants/config.py
ants/__init__.py
ants/lib.cpython-311-darwin.so
ants/decorators.py
ants/registration/registration.py
ants/registration/integrate_velocity_field.py
ants/registration/simulate_displacement_field.py
ants/registration/invert_displacement_field.py
ants/registration/affine_initializer.py
ants/registration/fit_thin_plate_spline_displacement_field.py
ants/registration/fit_bspline_displacement_field.py
ants/registration/__init__.py
ants/registration/landmark_transforms.py
ants/registration/build_template.py
ants/registration/average_transform.py
ants/registration/fit_bspline_object_to_scattered_data.py
ants/registration/compose_displacement_fields.py
ants/registration/create_jacobian_determinant_image.py
ants/registration/apply_transforms.py
ants/registration/create_warped_grid.py
ants/learn/__init__.py
ants/learn/decomposition.py
ants/core/__init__.py
ants/core/ants_transform.py
ants/core/ants_metric_io.py
ants/core/ants_metric.py
ants/core/ants_transform_io.py
ants/core/ants_image.py
ants/core/ants_image_io.py
ants/segmentation/functional_lung_segmentation.py
ants/segmentation/kelly_kapowski.py
ants/segmentation/prior_based_segmentation.py
ants/segmentation/atropos.py
ants/segmentation/joint_label_fusion.py
ants/segmentation/__init__.py
ants/segmentation/kmeans.py
ants/segmentation/fuzzy_spatial_cmeans_segmentation.py
ants/segmentation/otsu.py
ants/deeplearn/simulate_bias_field.py
ants/deeplearn/randomly_transform_image_data.py
ants/deeplearn/reconstruct_image_from_patches.py
ants/deeplearn/__init__.py
ants/deeplearn/regression_match_image.py
ants/deeplearn/extract_image_patches.py
ants/deeplearn/one_hot_segmentation.py
ants/deeplearn/data_augmentation.py
ants/deeplearn/histogram_warp_image_intensities.py
ants/deeplearn/cropping_and_padding_utilities.py
ants/label/label_stats.py
ants/label/multi_label_morphology.py
ants/label/label_geometry_measures.py
ants/label/label_overlap_measures.py
antspyx-0.6.2.dist-info/RECORD
antspyx-0.6.2.dist-info/WHEEL
antspyx-0.6.2.dist-info/METADATA
antspyx-0.6.2.dist-info/licenses/LICENSE
