Metadata-Version: 2.1
Name: antspyx
Version: 0.6.2
Summary: A fast medical imaging analysis library in Python with algorithms for registration, segmentation, and more.
Author-Email: "Brian B. Avants" <stnava@gmail.com>
License: Apache-2.0
Classifier: License :: OSI Approved :: Apache Software License
Project-URL: Homepage, https://github.com/antsx/antspy
Requires-Python: >=3.8
Requires-Dist: pandas
Requires-Dist: pyyaml
Requires-Dist: numpy<2.4.0
Requires-Dist: statsmodels
Requires-Dist: webcolors
Requires-Dist: matplotlib
Requires-Dist: Pillow
Requires-Dist: requests
Requires-Dist: scikit-learn
Requires-Dist: scipy<1.16
